{
    "A": "\ud835\udc68",
    "B": "\ud835\udc69",
    "C": "\ud835\udc6a",
    "D": "\ud835\udc6b",
    "E": "\ud835\udc6c",
    "F": "\ud835\udc6d",
    "G": "\ud835\udc6e",
    "H": "\ud835\udc6f",
    "I": "\ud835\udc70",
    "J": "\ud835\udc71",
    "K": "\ud835\udc72",
    "L": "\ud835\udc73",
    "M": "\ud835\udc74",
    "N": "\ud835\udc75",
    "O": "\ud835\udc76",
    "P": "\ud835\udc77",
    "Q": "\ud835\udc78",
    "R": "\ud835\udc79",
    "S": "\ud835\udc7a",
    "T": "\ud835\udc7b",
    "U": "\ud835\udc7c",
    "V": "\ud835\udc7d",
    "W": "\ud835\udc7e",
    "X": "\ud835\udc7f",
    "Y": "\ud835\udc80",
    "Z": "\ud835\udc81",
    "a": "\ud835\udc82",
    "b": "\ud835\udc83",
    "c": "\ud835\udc84",
    "d": "\ud835\udc85",
    "e": "\ud835\udc86",
    "f": "\ud835\udc87",
    "g": "\ud835\udc88",
    "h": "\ud835\udc89",
    "i": "\ud835\udc8a",
    "j": "\ud835\udc8b",
    "k": "\ud835\udc8c",
    "l": "\ud835\udc8d",
    "m": "\ud835\udc8e",
    "n": "\ud835\udc8f",
    "o": "\ud835\udc90",
    "p": "\ud835\udc91",
    "q": "\ud835\udc92",
    "r": "\ud835\udc93",
    "s": "\ud835\udc94",
    "t": "\ud835\udc95",
    "u": "\ud835\udc96",
    "v": "\ud835\udc97",
    "w": "\ud835\udc98",
    "x": "\ud835\udc99",
    "y": "\ud835\udc9a",
    "z": "\ud835\udc9b"
}